skypy/__init__.py
skypy/_astropy_init.py
skypy/conftest.py
skypy/example_mod.py
skypy/version.py
skypy/data/README.rst
skypy/example_subpkg/__init__.py
skypy/example_subpkg/setup_package.py
skypy/example_subpkg/tests/__init__.py
skypy/extern/__init__.py
skypy/tests/__init__.py
skypy/tests/coveragerc
skypy/tests/test_example.py
skypy/utils/__init__.py
skypy/utils/tests/__init__.py
skypy-0.0.dev2.dist-info/METADATA
skypy-0.0.dev2.dist-info/WHEEL
skypy-0.0.dev2.dist-info/entry_points.txt
skypy-0.0.dev2.dist-info/top_level.txt
skypy-0.0.dev2.dist-info/RECORD
